academylibrary/__init__.py
academylibrary/academylibrary.py
academylibrary-0.0.2.dist-info/METADATA
academylibrary-0.0.2.dist-info/WHEEL
academylibrary-0.0.2.dist-info/top_level.txt
academylibrary-0.0.2.dist-info/RECORD
