Metadata-Version: 2.1
Name: academylibrary
Version: 0.0.2
Summary: Academy4Summer Package
Author: Gilad Korngut
Author-email: theacademy4summer@gmail.com
Keywords: python,Course,Discord
Classifier: Development Status :: 1 - Planning
Classifier: Intended Audience :: Developers
Classifier: Programming Language :: Python :: 3
Classifier: Operating System :: Unix
Classifier: Operating System :: MacOS :: MacOS X
Classifier: Operating System :: Microsoft :: Windows
Requires-Dist: discord
Requires-Dist: pyautogui
